pymedooze/utils.py
pymedooze/_pymedooze.pypy310-pp73-x86_64-linux-gnu.so
pymedooze/libmp4v2-shared.so
pymedooze/_pymedooze.pyi
pymedooze/__init__.py
pymedooze/endpoint.py
pymedooze/transport.py
pymedooze-0.1.0b1.dist-info/RECORD
pymedooze-0.1.0b1.dist-info/METADATA
pymedooze-0.1.0b1.dist-info/WHEEL
pymedooze.libs/libselinux-0922c95c.so.1
pymedooze.libs/libpangocairo-1-b80816ef.0.so.0.4200.3
pymedooze.libs/libtheoraenc-b005fd1d.so.1.1.2
pymedooze.libs/libavcodec-785ca401.so.57.107.100
pymedooze.libs/liblzma-004595ca.so.5.2.2
pymedooze.libs/libcairo-55a37961.so.2.11512.0
pymedooze.libs/libuuid-f64cda11.so.1.3.0
pymedooze.libs/libthai-b24067ec.so.0.1.6
pymedooze.libs/libpango-1-875bd7a7.0.so.0.4200.3
pymedooze.libs/libmount-2c8ae47c.so.1.1.0
pymedooze.libs/libpng15-ce838cd1.so.15.13.0
pymedooze.libs/libblkid-fccc232f.so.1.1.0
pymedooze.libs/libgomp-a34b3233.so.1.0.0
pymedooze.libs/libxml2-3998bec4.so.2.9.1
pymedooze.libs/libcroco-0-9a800bf7.6.so.3.0.1
pymedooze.libs/libzvbi-6aa45ffe.so.0.13.2
pymedooze.libs/libpixman-1-f094a0b6.so.0.34.0
pymedooze.libs/libgdk_pixbuf-2-fd592e6b.0.so.0.3612.0
pymedooze.libs/libswscale-b560cc41.so.4.8.100
pymedooze.libs/libcrypto-d3570994.so.1.0.2k
pymedooze.libs/libkeyutils-dfe70bd6.so.1.5
pymedooze.libs/libspeex-56b87c1d.so.1.5.0
pymedooze.libs/libswresample-6876b584.so.2.9.100
pymedooze.libs/libcom_err-2abe824b.so.2.1
pymedooze.libs/libvo-amrwbenc-9973043b.so.0.0.4
pymedooze.libs/libmfx-4adb412c.so.0.0.0
pymedooze.libs/libx264-f0b04f03.so.148
pymedooze.libs/libvdpau-2737e7d5.so.1.0.0
pymedooze.libs/libXau-00ec42fe.so.6.0.0
pymedooze.libs/libvpx-6649f709.so.1.3.0
pymedooze.libs/libsoxr-6993ef22.so.0.1.1
pymedooze.libs/libssl-cd1d6220.so.1.0.2k
pymedooze.libs/libx265-a525a4fb.so.165
pymedooze.libs/libEGL-29b68110.so.1.1.0
pymedooze.libs/libfreetype-c0e61f0c.so.6.14.0
pymedooze.libs/libvorbis-02341991.so.0.4.6
pymedooze.libs/librsvg-2-2c11776f.so.2.40.20
pymedooze.libs/libgsm-ed01cacd.so.1.0.12
pymedooze.libs/libkrb5support-d0bcff84.so.0.1
pymedooze.libs/libnuma-428e8baf.so.1.0.0
